octoprint_file_check/__init__.py
octoprint_file_check/static/clientjs/file_check.js
octoprint_file_check/static/js/file_check.js
octoprint_file_check/templates/file_check_settings.jinja2
octoprint_file_check/templates/file_check_wizard_fullcheck.jinja2
octoprint_file_check/templates/snippets/fileCheckButton.jinja2
octoprint_file_check/translations/de/LC_MESSAGES/messages.mo
octoprint_file_check/translations/de/LC_MESSAGES/messages.po
OctoPrint_FileCheck-2024.11.12.dist-info/LICENSE
OctoPrint_FileCheck-2024.11.12.dist-info/METADATA
OctoPrint_FileCheck-2024.11.12.dist-info/WHEEL
OctoPrint_FileCheck-2024.11.12.dist-info/entry_points.txt
OctoPrint_FileCheck-2024.11.12.dist-info/top_level.txt
OctoPrint_FileCheck-2024.11.12.dist-info/RECORD
