Metadata-Version: 2.1
Name: OctoPrint-FileCheck
Version: 2024.11.12
Summary: Checks for common issues in uploaded files
Home-page: https://github.com/OctoPrint/OctoPrint-FileCheck
Author: Gina Häußge
Author-email: gina@octoprint.org
License: AGPLv3
Platform: UNKNOWN
Provides-Extra: develop
Requires-Dist: pre-commit ; extra == 'develop'
